<?xml version="1.0" encoding="UTF-8"?>
<?xml-model href="http://jetson.unl.edu/cdrh/schemas/vra-tei-strict.xsd"?>


<vra xmlns="http://www.vraweb.org/vracore4.htm"
    xmlns:tei="http://www.tei-c.org/ns/1.0">
    <collection id="zzz.00039">
        <agentSet>
            <display>V.W. Horton(?) of J. Gurney and Son</display>
            <agent>
                <name type="corporate" vocab="ULAN" refid="500116204">Gurney and Son</name>            
                <role vocab="AAT" refid="300025687">photographer</role>
            </agent>                
        </agentSet>        
        <dateSet>
            <display>1871</display>
            <date type="creation">                
                <earliestDate circa="false">1871</earliestDate>
                <latestDate circa="false">1871</latestDate>
            </date>
        </dateSet>
        <descriptionSet>            
            <description source="Walt Whitman Archive"><tei:p>Nearly identical to another photo from this session, but shaded on the opposite side.</tei:p><tei:p>There is no Saunders number for this photograph.</tei:p></description>
        </descriptionSet>           
        <relationSet>
            <relation type="sourceFor" relids="owu.00047"/>
        </relationSet>            
        <subjectSet>
            <subject>
                <term type="personalName" vocab="lccn" refid="n79081476">Whitman, Walt, 1819-1892</term>
            </subject>
            <subject>
                <term type="geographicPlace" vocab="lccn" refid="n79007751"> New York (N.Y.)</term>
            </subject>
        </subjectSet>
        <techniqueSet>
            <technique vocab="AAT" refid="300046300">photograph</technique>
        </techniqueSet>   
        <titleSet>
            <title type="descriptive">Walt Whitman by V.W. Horton(?) of J. Gurney and Son, 1871</title>
        </titleSet>  
        <work id="owu.00047" pref="true">
            <agentSet>
                <agent>
                    <name>Unknown</name>
                    <role vocab="AAT" refid="300121785">inscriber</role>
                </agent>
            </agentSet>
            <inscriptionSet>            
                <inscription>
                    <author>Unknown</author>
                    <position>On the recto, under the portrait</position>
                    <text type="other">Photo by Gurney</text>
                </inscription>            
            </inscriptionSet> 
            <locationSet>
                <location type="repository">
                    <name>Ohio Wesleyan University, Bayley Collection</name>
                </location>
            </locationSet>
            <measurementsSet>
                <measurements>Unknown</measurements>
            </measurementsSet>
            <relationSet>
                <relation type="versionOf" relids="zzz.00039"/>
                <relation type="imageIs" relids="image051"/>
            </relationSet>
            <rightsSet>
                <rights type="other">
                    <text>Contact holding institution.</text>
                </rights>
            </rightsSet>                    
            <worktypeSet>
                <worktype vocab="AAT" refid="300127141">carte-de-visite</worktype>            
            </worktypeSet>
            <image id="image051">
                <agentSet>
                    <agent>
                        <name type="corporate">Ohio Wesleyan University, Bayley Collection</name>
                        <role>creator of master digital image</role>
                    </agent>
                </agentSet>
                <dateSet>
                    <date>
                        <earliestDate circa="true">1995</earliestDate>
                        <latestDate circa="true">2000</latestDate>
                    </date>
                </dateSet>
                <relationSet>
                    <relation type="imageOf" relids="owu.00047"/>
                </relationSet>
                <rightsSet>
                    <rights type="other">
                        <rightsHolder>Ohio Wesleyan University, Bayley Collection</rightsHolder>
                        <text>Used with permission. For permission to reproduce this image, contact the holding institution.</text>
                    </rights>
                </rightsSet> 
                <worktypeSet>
                    <worktype vocab="AAT" refid="300215302">digital image</worktype>
                </worktypeSet>
            </image>
        </work>    
    </collection>        
</vra>
